estnltk_neural/__init__.py
estnltk_neural/common.py
estnltk_neural/helpers/__init__.py
estnltk_neural/helpers/neural_morph_logger.py
estnltk_neural/helpers/neural_morph_progbar.py
estnltk_neural/taggers/__init__.py
estnltk_neural/taggers/coreference/__init__.py
estnltk_neural/taggers/coreference/v1/__init__.py
estnltk_neural/taggers/coreference/v1/coreference_api.py
estnltk_neural/taggers/coreference/v1/coreference_features.py
estnltk_neural/taggers/coreference/v1/coreference_tagger.py
estnltk_neural/taggers/coreference/v1/generate_pairs.py
estnltk_neural/taggers/coreference/v1/utilities.py
estnltk_neural/taggers/embeddings/__init__.py
estnltk_neural/taggers/embeddings/bert/__init__.py
estnltk_neural/taggers/embeddings/bert/bert_tagger.py
estnltk_neural/taggers/embeddings/bert/bert_tokens_to_words_rewriter.py
estnltk_neural/taggers/embeddings/bert/bert_transformer.py
estnltk_neural/taggers/embeddings/bert/roberta_tagger.py
estnltk_neural/taggers/embeddings/bert/model-data/__init__.py
estnltk_neural/taggers/ner/__init__.py
estnltk_neural/taggers/ner/estbertner_tagger.py
estnltk_neural/taggers/neural_morph/__init__.py
estnltk_neural/taggers/neural_morph/bert_based/__init__.py
estnltk_neural/taggers/neural_morph/bert_based/bert_morph_tagger.py
estnltk_neural/taggers/neural_morph/glilem/__init__.py
estnltk_neural/taggers/neural_morph/glilem/glilem_tagger.py
estnltk_neural/taggers/neural_morph/glilem/rule_processor.py
estnltk_neural/taggers/neural_morph/glilem/vabamorf_glilem_lemmatizer.py
estnltk_neural/taggers/neural_morph/new_neural_morph/__init__.py
estnltk_neural/taggers/neural_morph/new_neural_morph/general_utils.py
estnltk_neural/taggers/neural_morph/new_neural_morph/neural_2_vabamorf.py
estnltk_neural/taggers/neural_morph/new_neural_morph/neural_morph_tagger.py
estnltk_neural/taggers/neural_morph/new_neural_morph/rnn_util.py
estnltk_neural/taggers/neural_morph/new_neural_morph/vabamorf_2_neural.py
estnltk_neural-1.7.4.dist-info/LICENSE
estnltk_neural-1.7.4.dist-info/METADATA
estnltk_neural-1.7.4.dist-info/WHEEL
estnltk_neural-1.7.4.dist-info/top_level.txt
estnltk_neural-1.7.4.dist-info/RECORD
