Metadata-Version: 2.2
Name: estnltk_neural
Version: 1.7.4
Summary: EstNLTK neural -- EstNLTK's linguistic analysis based on neural models
Home-page: https://github.com/estnltk/estnltk
Author: University of Tartu
Author-email: Siim Orasmaa <siim.orasmaa@ut.ee>, Sven Laur <swen@math.ut.ee>, Paul Tammo <paul.tammo@gmail.com>
License: Dual License: GPL-2.0 OR Apache-2.0
Project-URL: homepage, https://github.com/estnltk/estnltk
Project-URL: documentation, https://github.com/estnltk/estnltk/tree/main/tutorials
Project-URL: repository, https://github.com/estnltk/estnltk/tree/main/estnltk_neural
Project-URL: changelog, https://github.com/estnltk/estnltk/blob/main/CHANGELOG.md
Keywords: Estonian natural language processing,Estonian linguistic processing
Classifier: Intended Audience :: Developers
Classifier: Intended Audience :: Education
Classifier: Intended Audience :: Science/Research
Classifier: Intended Audience :: Information Technology
Classifier: Operating System :: OS Independent
Classifier: Programming Language :: Python :: 3.9
Classifier: Programming Language :: Python :: 3.10
Classifier: Programming Language :: Python :: 3.11
Classifier: Programming Language :: Python :: 3.12
Classifier: Topic :: Scientific/Engineering
Classifier: Topic :: Scientific/Engineering :: Artificial Intelligence
Classifier: Topic :: Scientific/Engineering :: Information Analysis
Classifier: Topic :: Text Processing
Classifier: Topic :: Text Processing :: Linguistic
Requires-Python: >=3.9
License-File: LICENSE
Requires-Dist: estnltk-core>=1.7.4
Requires-Dist: estnltk>=1.7.4
Requires-Dist: torch
Requires-Dist: transformers
Requires-Dist: stanza
Requires-Dist: packaging
Provides-Extra: tests
Requires-Dist: pytest; extra == "tests"
Provides-Extra: bert-morph
Requires-Dist: sentencepiece; extra == "bert-morph"
Provides-Extra: neural-morph
Requires-Dist: tensorflow<=1.15.5; extra == "neural-morph"
Provides-Extra: coreference-v1
Requires-Dist: scikit-learn; extra == "coreference-v1"
Requires-Dist: xgboost; extra == "coreference-v1"
Requires-Dist: gensim; extra == "coreference-v1"
Provides-Extra: glilem
Requires-Dist: gliner; extra == "glilem"
Dynamic: home-page
